<?xml version="1.0" encoding="utf-8"?>
<Settings xmlns:xsi="http://www.w3.org/2001/XMLSchema-instance" xmlns:xsd="http://www.w3.org/2001/XMLSchema" xmlns="http://alternetsoft.com/es/formdesigner">
  <AssemblyReferences>
    <AssemblyReference>
      <Path>C:\develop\git\AlternetStudio\Demo\FormDesigner\Demos\FormDesigner\bin\Debug\net7.0-windows\Alternet.Editor.v9.dll</Path>
    </AssemblyReference>
    <AssemblyReference>
      <Path>C:\develop\git\AlternetStudio\Demo\FormDesigner\Demos\FormDesigner\bin\Debug\net7.0-windows\Alternet.Syntax.v9.dll</Path>
    </AssemblyReference>
    <AssemblyReference>
      <Path>C:\develop\git\AlternetStudio\Demo\FormDesigner\Demos\FormDesigner\bin\Debug\net7.0-windows\Alternet.Common.v9.dll</Path>
    </AssemblyReference>
  </AssemblyReferences>
</Settings>